proj.v
module main(
    input wire clk,
    input wire reset,
    input wire Entry_sensor,
    input wire Exit_sensor,
    input wire [1:0] Exit_parking,
    output wire Full_light,
    output wire Door_Open_light,
    output reg [3:0] parkings,
    output reg [2:0] capacity,
    output reg [1:0] location,
    output reg [2:0] state
);

parameter IDLE = 3'b000,
          CHECK_ENTRY = 3'b001,
          CHECK_EXIT = 3'b010,
          FULL = 3'b011,
          DOOR_OPEN = 3'b100,
          PARK_CAR = 3'b101,
          UPDATE_DISPLAY = 3'b110;

reg [2:0] current_state, next_state;

wire open_door;
wire full;
reg internal_full;
reg internal_open_door;



assign full = internal_full;
assign open_door = internal_open_door;



reg [31:0] delay_counter;

FrequencyDividerController controller(
    .clk(clk),
    .reset(reset),
    .full(full),
    .open_door(open_door),
    .open_door_output(Door_Open_light),
    .full_output(Full_light)
);

initial begin
    current_state = IDLE;
    parkings = 4'b0000;
    location = 2'b00;
    capacity = 3'b100;
    delay_counter = 0;
end

always @(posedge clk or posedge reset) begin
    state <= current_state;
    if (reset) begin
        current_state <= IDLE;
    end else begin
        current_state <= next_state;
    end
end

always @(posedge clk) begin
    if (reset) begin
        delay_counter <= 0;
    end 
    else if (internal_open_door || internal_full) begin
        if (current_state == FULL) begin
            if (delay_counter < 14) // 6 ثانیه
                delay_counter <= delay_counter + 1;
            else
                delay_counter <= 0; 
        end else if (current_state == DOOR_OPEN) begin
            if (delay_counter < 51) // 10 ثانیه
                delay_counter <= delay_counter + 1;
            else
                delay_counter <= 0; 
        end 
        else begin
            delay_counter <= 0; 
        end
    end
    else
        delay_counter <= 0;
end

always @(posedge clk) begin
    case (current_state)
        IDLE: begin
            next_state = Entry_sensor ? CHECK_ENTRY :
                         Exit_sensor ? CHECK_EXIT : IDLE;
        end
        CHECK_ENTRY: begin
            if (capacity == 0) 
                next_state = FULL;
            else begin
                parkings[location] = 1;
                location <= (parkings[0] == 0) ? 2'b00 :
                            (parkings[1] == 0) ? 2'b01 :
                            (parkings[2] == 0) ? 2'b10 : 2'b11;
                capacity <= capacity - 1;
                next_state = DOOR_OPEN;
            end
        end
        FULL: begin
            internal_full = 1;
            if (delay_counter == 13)begin
                internal_full = 0;
                next_state = IDLE;
            end
            else
                next_state = FULL;
        end
        DOOR_OPEN: begin
            internal_open_door = 1;
            if (delay_counter == 50)begin
                internal_open_door = 0;
                next_state = IDLE;
            end
            else
                next_state = DOOR_OPEN;
        end
        CHECK_EXIT: begin
            if(capacity == 3'b000)begin
                next_state = IDLE;
            end
            else begin
            parkings[Exit_parking] = 0;
            location <= (parkings[0] == 0) ? 2'b00 :
                        (parkings[1] == 0) ? 2'b01 :
                        (parkings[2] == 0) ? 2'b10 : 2'b11;
            capacity = capacity + 1;
            next_state = IDLE;
            end
        end
    endcase
end
endmodule

module FrequencyDividerController (
    input wire clk,
    input wire reset,
    input wire full,
    input wire open_door,
    output reg open_door_output,
    output reg full_output
);

reg [3:0] full_counter;
reg [23:0] door_counter;
reg [25:0] clk_divider_1Hz;
reg [24:0] clk_divider_2Hz;

initial begin
    full_counter = 0;
    door_counter = 0;
    full_output = 0;
    open_door_output = 0;
end

always @(posedge clk or posedge reset) begin
    if (reset) begin
        clk_divider_1Hz <= 0;
        clk_divider_2Hz <= 0;
        full_counter <= 0;
        door_counter <= 0;
        full_output <= 0;
        open_door_output <= 0;
    end 
    else begin
        if(open_door) begin
            full_output <= 0;
            full_counter <= 0;
            if (door_counter < 10) begin 
                if (clk_divider_2Hz == 2) begin
                    door_counter <= door_counter + 1;
                    open_door_output <= ~open_door_output;
                    clk_divider_2Hz <= 0;
                end
                else begin
                    clk_divider_2Hz <= clk_divider_2Hz + 1;
                end
            end 
            else begin
                open_door_output <= 0;
            end
        end
        else if(full) begin
                open_door_output <= 0;
                door_counter <= 0;
                if (full_counter < 6) begin 
                    if (clk_divider_1Hz == 2) begin
                        full_counter <= full_counter + 1;   
                        full_output <= ~full_output;
                        clk_divider_1Hz <= 0;
                    end
                    else begin
                        clk_divider_1Hz <= clk_divider_1Hz + 1;
                    end
                end 
                else begin
                    full_output <= 0;
                end
            end
            else begin
                open_door_output <= 0;
                full_counter <= 0;
                door_counter <= 0;
                full_output <= 0;
            end
    end
end

endmodule
module main_tb;

    reg clk;
    reg reset;
    reg Entry_sensor;
    reg Exit_sensor;
    reg [1:0] Exit_parking;

    wire Full_light;
    wire Door_Open_light;
    wire [3:0] parkings;
    wire [2:0] capacity;
    wire [1:0] location;
    wire [2:0] state;

    // Instantiate the main module
    main uut (
        .clk(clk),
        .reset(reset),
        .Entry_sensor(Entry_sensor),
        .Exit_sensor(Exit_sensor),
        .Exit_parking(Exit_parking),
        .Full_light(Full_light),
        .Door_Open_light(Door_Open_light),
        .parkings(parkings),
        .capacity(capacity),
        .location(location),
        .state(state)
    );

    // Clock generation
    initial begin
        clk = 0;
        forever #1 clk = ~clk; // 50 MHz clock
    end

    // Test sequence
    initial begin
        $dumpfile("main_tb.vcd"); // Generate waveform file
        $dumpvars(1, main_tb);

        // Initial conditions
        reset = 1;
        Entry_sensor = 0;
        Exit_sensor = 0;
        Exit_parking = 2'b00;

        #2 reset = 0; // Deassert reset

        // Test: Entry to parking
        #50 Entry_sensor = 1; // Car at entry
        #100 Entry_sensor = 0; // Car entered

        // Test: Another entry
        #50 Entry_sensor = 1;
        #100 Entry_sensor = 0;

        // Test: Another entry
        #50 Entry_sensor = 1;
        #100 Entry_sensor = 0;

        // Test: Another entry
        #50 Entry_sensor = 1;
        #100 Entry_sensor = 0;

        // Test: Another entry
        #50 Entry_sensor = 1;
        #50 Entry_sensor = 0;

        // Wait for FULL state to complete (6 seconds)
        #100;

        // Test: Exit from parking
        #10 Exit_sensor = 1;
        Exit_parking = 2'b01; // Car exiting from location 1
        #40 Exit_sensor = 0;

        // Wait for DOOR_OPEN state to complete (10 seconds)
        #100;

        // Test: Reset and reinitialize
        #20 reset = 1;
        #40 reset = 0;

        #200 $finish; // End simulation
    end

    // Monitor signals
    initial begin
        $monitor("Time: %d | Reset: %b | Entry: %b | Exit: %b | Full: %b | Door: %b | Parkings: %b | Capacity: %b | Location: %b | State: %b",
            $time, reset, Entry_sensor, Exit_sensor, Full_light, Door_Open_light, parkings, capacity, location , state);
    end
endmodule

main_tb.vcd
$date
	Tue Dec 24 12:36:24 2024
$end
$version
	Icarus Verilog
$end
$timescale
	1s
$end
$scope module main_tb $end
$var wire 3 ! state [2:0] $end
$var wire 4 " parkings [3:0] $end
$var wire 2 # location [1:0] $end
$var wire 3 $ capacity [2:0] $end
$var wire 1 % Full_light $end
$var wire 1 & Door_Open_light $end
$var reg 1 ' Entry_sensor $end
$var reg 2 ( Exit_parking [1:0] $end
$var reg 1 ) Exit_sensor $end
$var reg 1 * clk $end
$var reg 1 + reset $end
$upscope $end
$enddefinitions $end
$comment Show the parameter values. $end
$dumpall
$end
#0
$dumpvars
1+
0*
0)
b0 (
0'
0&
0%
b100 $
b0 #
b0 "
b0 !
$end
#1
1*
#2
0*
0+
#3
1*
#4
0*
#5
1*
#6
0*
#7
1*
#8
0*
#9
1*
#10
0*
#11
1*
#12
0*
#13
1*
#14
0*
#15
1*
#16
0*
#17
1*
#18
0*
#19
1*
#20
0*
#21
1*
#22
0*
#23
1*
#24
0*
#25
1*
#26
0*
#27
1*
#28
0*
#29
1*
#30
0*
#31
1*
#32
0*
#33
1*
#34
0*
#35
1*
#36
0*
#37
1*
#38
0*
#39
1*
#40
0*
#41
1*
#42
0*
#43
1*
#44
0*
#45
1*
#46
0*
#47
1*
#48
0*
#49
1*
#50
0*
#51
1*
#52
0*
1'
#53
1*
#54
0*
#55
b1 !
b11 $
b1 #
b1 "
1*
#56
0*
#57
b100 !
1*
#58
0*
#59
1*
#60
0*
#61
1&
1*
#62
0*
#63
1*
#64
0*
#65
1*
#66
0*
#67
0&
1*
#68
0*
#69
1*
#70
0*
#71
1*
#72
0*
#73
1&
1*
#74
0*
#75
1*
#76
0*
#77
1*
#78
0*
#79
0&
1*
#80
0*
#81
1*
#82
0*
#83
1*
#84
0*
#85
1&
1*
#86
0*
#87
1*
#88
0*
#89
1*
#90
0*
#91
0&
1*
#92
0*
#93
1*
#94
0*
#95
1*
#96
0*
#97
1&
1*
#98
0*
#99
1*
#100
0*
#101
1*
#102
0*
#103
0&
1*
#104
0*
#105
1*
#106
0*
#107
1*
#108
0*
#109
1&
1*
#110
0*
#111
1*
#112
0*
#113
1*
#114
0*
#115
0&
1*
#116
0*
#117
1*
#118
0*
#119
1*
#120
0*
#121
1*
#122
0*
#123
1*
#124
0*
#125
1*
#126
0*
#127
1*
#128
0*
#129
1*
#130
0*
#131
1*
#132
0*
#133
1*
#134
0*
#135
1*
#136
0*
#137
1*
#138
0*
#139
1*
#140
0*
#141
1*
#142
0*
#143
1*
#144
0*
#145
1*
#146
0*
#147
1*
#148
0*
#149
1*
#150
0*
#151
1*
#152
0*
0'
#153
1*
#154
0*
#155
1*
#156
0*
#157
1*
#158
0*
#159
b0 !
1*
