proj.v
module main(
    input wire clk,
    input wire reset,
    input wire Entry_sensor,
    input wire Exit_sensor,
    input wire [1:0] Exit_parking,
    output wire Full_light,
    output wire Door_Open_light,
    output reg [3:0] parkings,
    output reg [2:0] capacity,
    output reg [1:0] location,
    output reg [2:0] state,
    output reg internal_full,
    output reg internal_open_door
);

parameter IDLE = 3'b000,
          CHECK_ENTRY = 3'b001,
          CHECK_EXIT = 3'b010,
          FULL = 3'b011,
          DOOR_OPEN = 3'b100,
          UPDATE_DISPLAY = 3'b110;

reg [2:0] current_state, next_state;

wire open_door;
wire full;


assign full = internal_full;
assign open_door = internal_open_door;



reg [31:0] delay_counter;

FrequencyDividerController controller(
    .clk(clk),
    .reset(reset),
    .full(full),
    .open_door(open_door),
    .open_door_output(Door_Open_light),
    .full_output(Full_light)
);

initial begin
    current_state = IDLE;
    internal_full = 0;
    internal_open_door =0;
    parkings = 4'b0000;
    location = 2'b00;
    capacity = 3'b100;
    delay_counter = 0;
end

always @(posedge clk or posedge reset) begin
    state <= current_state;
    if (reset) begin
        parkings = 4'b0000;
        location = 2'b00;
        capacity = 3'b100;
        delay_counter = 0;
        current_state <= IDLE;
    end else begin
        current_state <= next_state;
    end
end

always @(posedge clk) begin
    if (reset) begin
        delay_counter <= 0;
    end 
    else if (internal_open_door || internal_full) begin
        if (current_state == FULL) begin
            if (delay_counter < 41) 
                delay_counter <= delay_counter + 1;
            else
                delay_counter <= 0; 
        end else if (current_state == DOOR_OPEN) begin
            if (delay_counter < 51) 
                delay_counter <= delay_counter + 1;
            else
                delay_counter <= 0; 
        end 
        else begin
            delay_counter <= 0; 
        end
    end
    else
        delay_counter <= 0;
end

always @(posedge clk) begin
    case (current_state)
        IDLE: begin
            next_state = Entry_sensor ? CHECK_ENTRY :
                         Exit_sensor ? CHECK_EXIT : IDLE;
        end
        CHECK_ENTRY: begin
            if (capacity == 0) 
                next_state = FULL;
            else begin
                parkings[location] = 1;
                location <= (parkings[0] == 0) ? 2'b00 :
                            (parkings[1] == 0) ? 2'b01 :
                            (parkings[2] == 0) ? 2'b10 : 2'b11;
                capacity <= capacity - 1;
                next_state = DOOR_OPEN;
            end
        end
        CHECK_EXIT: begin
            if(capacity == 3'b100 | parkings[Exit_parking] == 0)begin
                next_state = IDLE;
            end 
            else begin
            parkings[Exit_parking] = 0;
            location <= (parkings[0] == 0) ? 2'b00 :
                        (parkings[1] == 0) ? 2'b01 :
                        (parkings[2] == 0) ? 2'b10 : 2'b11;
            capacity = capacity + 1;
            next_state = DOOR_OPEN;
            end
        end
        FULL: begin
        //3times 1s
            internal_full = 1;
            if (delay_counter == 36)begin
                internal_full = 0;
                next_state = IDLE;
            end
            else
                next_state = FULL;
        end
        DOOR_OPEN: begin
            //10 s / 2hz
            internal_open_door = 1;
            if (delay_counter == 35)begin
                internal_open_door = 0;
                next_state = IDLE;
            end
            else
                next_state = DOOR_OPEN;
        end
    endcase
end
endmodule

module FrequencyDividerController (
    input wire clk,
    input wire reset,
    input wire full,
    input wire open_door,
    output reg open_door_output, // open door 1
    output reg full_output // full 1
);

reg [3:0] full_counter;
reg [23:0] door_counter;
reg [25:0] clk_divider_1Hz;
reg [24:0] clk_divider_2Hz;

initial begin
    full_counter = 0;
    door_counter = 0;
    full_output = 0;
    open_door_output = 0;
end

always @(posedge clk or posedge reset) begin
    if (reset) begin
        clk_divider_1Hz <= 0;
        clk_divider_2Hz <= 0;
        full_counter <= 0;
        door_counter <= 0;
        full_output <= 0;
        open_door_output <= 0;
    end 
    else begin
        if(open_door) begin
            full_output <= 0;
            full_counter <= 0;
            if (door_counter < 10) begin 
                if (clk_divider_2Hz == 2) begin
                    door_counter <= door_counter + 1;
                    open_door_output <= ~open_door_output;
                    clk_divider_2Hz <= 0;
                end
                else begin
                    clk_divider_2Hz <= clk_divider_2Hz + 1;
                end
            end 
            else begin
                open_door_output <= 0;
            end
        end
        else if(full) begin
                open_door_output <= 0;
                door_counter <= 0;
                if (full_counter < 6) begin 
                    if (clk_divider_1Hz == 2) begin
                        full_counter <= full_counter + 1;   
                        full_output <= ~full_output;
                        clk_divider_1Hz <= 0;
                    end
                    else begin
                        clk_divider_1Hz <= clk_divider_1Hz + 1;
                    end
                end 
                else begin
                    full_output <= 0;
                end
            end
            else begin
                open_door_output <= 0;
                full_counter <= 0;
                door_counter <= 0;
                full_output <= 0;
            end
    end
end

endmodule
module main_tb;

    reg clk;
    reg reset;
    reg Entry_sensor;
    reg Exit_sensor;
    reg [1:0] Exit_parking;

    wire Full_light;
    wire Door_Open_light;
    wire [3:0] parkings;
    wire [2:0] capacity;
    wire [1:0] location;
    wire [2:0] state;
    wire internal_full;
    wire internal_open_door;

    // Instantiate the main module
    main uut (
        .clk(clk),
        .reset(reset),
        .Entry_sensor(Entry_sensor),
        .Exit_sensor(Exit_sensor),
        .Exit_parking(Exit_parking),
        .Full_light(Full_light),
        .Door_Open_light(Door_Open_light),
        .parkings(parkings),
        .capacity(capacity),
        .location(location),
        .state(state),
        .internal_full(internal_full),
        .internal_open_door(internal_open_door)
    );

    // Clock generation
    initial begin
        clk = 0;
        forever #12.5 clk = ~clk; 
    end



    integer input_file, output_file, scan_file;
    reg [3:0] input_data;

    // Test sequence
    initial begin
        $dumpfile("main_tb.vcd");
        $dumpvars(0, main_tb);

        reset = 1;
        Entry_sensor = 0;
        Exit_sensor = 0;
        Exit_parking = 2'b00;
        input_data = 4'b0000;
        #25;
        reset = 0;
        #15;


        input_file = $fopen("input.txt", "r");
        output_file = $fopen("output.txt", "w");

        if (input_file == 0 || output_file == 0) begin
            $display("Failed to open file.");
            $finish;
        end

        while (!$feof(input_file)) begin
            scan_file = $fscanf(input_file, "%4b\n", input_data);
            Entry_sensor = input_data[3];
            Exit_sensor = input_data[2];
            Exit_parking = input_data[1:0];
            $display("Read input: Entry_sensor=%b, Exit_sensor = %b , Exit_Parking=%b", Entry_sensor, Exit_sensor, Exit_parking); 
            #100;
            if (capacity == 0) 
            begin
                $fwrite(output_file, "%b%b%b%b [%d,-]\t", parkings[3] , parkings[2] , parkings[1] , parkings[0], capacity);
            end else
            begin
                $fwrite(output_file, "%b%b%b%b [%d,%d]\t", parkings[3] , parkings[2] , parkings[1] , parkings[0], capacity, location);
            end
            if (internal_open_door) begin
                $fwrite(output_file, "Door");
            end else if (internal_full) begin
                $fwrite(output_file, "Full");
            end
            $fwrite(output_file, "\n");
            #890;
        end

        $fclose(input_file);
        $fclose(output_file);
        $finish;
    end

    // Monitor signals
    initial begin
        $monitor("Time: %d | Reset: %b | Entry: %b | Exit: %b | Full: %b | Door: %b | Parkings: %b | Capacity: %b | Location: %b | State: %b",
            $time, reset, Entry_sensor, Exit_sensor, Full_light, Door_Open_light, parkings, capacity, location , state);
    end
endmodule

main_tb.vcd
$date
	Mon Dec 30 21:37:36 2024
$end
$version
	Icarus Verilog
$end
$timescale
	1s
$end
$scope module main_tb $end
$var wire 3 ! state [2:0] $end
$var wire 4 " parkings [3:0] $end
$var wire 2 # location [1:0] $end
$var wire 1 $ internal_open_door $end
$var wire 1 % internal_full $end
$var wire 3 & capacity [2:0] $end
$var wire 1 ' Full_light $end
$var wire 1 ( Door_Open_light $end
$var reg 1 ) Entry_sensor $end
$var reg 2 * Exit_parking [1:0] $end
$var reg 1 + Exit_sensor $end
$var reg 1 , clk $end
$var reg 4 - input_data [3:0] $end
$var reg 1 . reset $end
$var integer 32 / input_file [31:0] $end
$var integer 32 0 output_file [31:0] $end
$var integer 32 1 scan_file [31:0] $end
$scope module uut $end
$var wire 1 ) Entry_sensor $end
$var wire 2 2 Exit_parking [1:0] $end
$var wire 1 + Exit_sensor $end
$var wire 1 , clk $end
$var wire 1 3 full $end
$var wire 1 4 open_door $end
$var wire 1 . reset $end
$var wire 1 ' Full_light $end
$var wire 1 ( Door_Open_light $end
$var parameter 3 5 CHECK_ENTRY $end
$var parameter 3 6 CHECK_EXIT $end
$var parameter 3 7 DOOR_OPEN $end
$var parameter 3 8 FULL $end
$var parameter 3 9 IDLE $end
$var parameter 3 : UPDATE_DISPLAY $end
$var reg 3 ; capacity [2:0] $end
$var reg 3 < current_state [2:0] $end
$var reg 32 = delay_counter [31:0] $end
$var reg 1 % internal_full $end
$var reg 1 $ internal_open_door $end
$var reg 2 > location [1:0] $end
$var reg 3 ? next_state [2:0] $end
$var reg 4 @ parkings [3:0] $end
$var reg 3 A state [2:0] $end
$scope module controller $end
$var wire 1 , clk $end
$var wire 1 3 full $end
$var wire 1 4 open_door $end
$var wire 1 . reset $end
$var reg 26 B clk_divider_1Hz [25:0] $end
$var reg 25 C clk_divider_2Hz [24:0] $end
$var reg 24 D door_counter [23:0] $end
$var reg 4 E full_counter [3:0] $end
$var reg 1 ' full_output $end
$var reg 1 ( open_door_output $end
$upscope $end
$upscope $end
$upscope $end
$enddefinitions $end
$comment Show the parameter values. $end
$dumpall
b110 :
b0 9
b11 8
b100 7
b10 6
b1 5
$end
#0
$dumpvars
b0 E
b0 D
b0 C
b0 B
b0 A
b0 @
bx ?
b0 >
b0 =
b0 <
b100 ;
04
03
b0 2
bx 1
bx 0
bx /
1.
b0 -
0,
0+
b0 *
0)
0(
0'
b100 &
0%
0$
b0 #
b0 "
b0 !
$end
#13
b0 ?
1,
#25
0.
#26
0,
#39
1,
#40
b1 1
b10000000000000000000000000000100 0
b10000000000000000000000000000011 /
#52
0,
#65
1,
#78
0,
#91
1,
#104
0,
#117
1,
#130
0,
#143
1,
#156
0,
#169
1,
#182
0,
#195
1,
#208
0,
#221
1,
#234
0,
#247
1,
#260
0,
#273
1,
#286
0,
#299
1,
#312
0,
#325
1,
#338
0,
#351
1,
#364
0,
#377
1,
#390
0,
#403
1,
#416
0,
#429
1,
#442
0,
#455
1,
#468
0,
#481
1,
#494
0,
#507
1,
#520
0,
#533
1,
#546
0,
#559
1,
#572
0,
#585
1,
#598
0,
#611
1,
#624
0,
#637
1,
#650
0,
#663
1,
#676
0,
#689
1,
#702
0,
#715
1,
#728
0,
#741
1,
#754
0,
#767
1,
#780
0,
#793
1,
#806
0,
#819
1,
#832
0,
#845
1,
#858
0,
#871
1,
#884
0,
#897
1,
#910
0,
#923
1,
#936
0,
#949
1,
#962
0,
#975
1,
#988
0,
#1001
1,
#1014
0,
#1027
1,
#1030
1)
b1000 -
#1040
0,
#1053
b1 <
b1 ?
1,
#1066
0,
#1079
b100 <
b1 !
b1 A
b11 &
b11 ;
b1 #
b1 >
b100 ?
b1 "
b1 @
1,
#1092
0,
#1105
b100 !
b100 A
b1 C
b1 =
14
1$
1,
#1118
0,
#1131
b10 C
b10 =
1,
#1144
0,
#1157
b0 C
1(
b1 D
b11 =
1,
#1170
0,
#1183
b1 C
b100 =
1,
#1196
0,
#1209
b10 C
b101 =
1,
#1222
0,
#1235
b0 C
0(
b10 D
b110 =
1,
#1248
0,
#1261
b1 C
b111 =
1,
#1274
0,
#1287
b10 C
b1000 =
1,
#1300
0,
#1313
b0 C
1(
b11 D
b1001 =
1,
#1326
0,
#1339
b1 C
b1010 =
1,
#1352
0,
#1365
b10 C
b1011 =
1,
#1378
0,
#1391
b0 C
0(
b100 D
b1100 =
1,
#1404
0,
#1417
b1 C
b1101 =
1,
#1430
0,
#1443
b10 C
b1110 =
1,
#1456
0,
#1469
b0 C
1(
b101 D
b1111 =
1,
#1482
0,
#1495
b1 C
b10000 =
1,
#1508
0,
#1521
b10 C
b10001 =
1,
#1534
0,
#1547
b0 C
0(
b110 D
b10010 =
1,
#1560
0,
#1573
b1 C
b10011 =
1,
#1586
0,
#1599
b10 C
b10100 =
1,
#1612
0,
#1625
b0 C
1(
b111 D
b10101 =
1,
#1638
0,
#1651
b1 C
b10110 =
1,
#1664
0,
#1677
b10 C
b10111 =
1,
#1690
0,
#1703
b0 C
0(
b1000 D
b11000 =
1,
#1716
0,
#1729
b1 C
b11001 =
1,
#1742
0,
#1755
b10 C
b11010 =
1,
#1768
0,
#1781
b0 C
1(
b1001 D
b11011 =
1,
#1794
0,
#1807
b1 C
b11100 =
1,
#1820
0,
#1833
b10 C
b11101 =
1,
#1846
0,
#1859
b0 C
0(
b1010 D
b11110 =
1,
#1872
0,
#1885
b11111 =
1,
#1898
0,
#1911
b100000 =
1,
#1924
0,
#1937
b100001 =
1,
#1950
0,
#1963
b100010 =
1,
#1976
0,
#1989
b100011 =
1,
#2002
0,
#2015
b0 D
b0 <
b100100 =
b0 ?
04
0$
1,
#2020
b1 *
b1 2
b1001 -
#2028
0,
#2041
b1 <
b0 !
b0 A
b0 =
b1 ?
1,
#2054
0,
#2067
b100 <
b1 !
b1 A
b10 &
b10 ;
b10 #
b10 >
b100 ?
b11 "
b11 @
1,
#2080
0,
#2093
b100 !
b100 A
b1 C
b1 =
14
1$
1,
#2106
0,
#2119
b10 C
b10 =
1,
#2132
0,
#2145
b0 C
1(
b1 D
b11 =
1,
#2158
0,
#2171
b1 C
b100 =
1,
#2184
0,
#2197
b10 C
b101 =
1,
#2210
0,
#2223
b0 C
0(
b10 D
b110 =
1,
#2236
0,
#2249
b1 C
b111 =
1,
#2262
0,
#2275
b10 C
b1000 =
1,
#2288
0,
#2301
b0 C
1(
b11 D
b1001 =
1,
#2314
0,
#2327
b1 C
b1010 =
1,
#2340
0,
#2353
b10 C
b1011 =
1,
#2366
0,
#2379
b0 C
0(
b100 D
b1100 =
1,
#2392
0,
#2405
b1 C
b1101 =
1,
#2418
0,
#2431
b10 C
b1110 =
1,
#2444
0,
#2457
b0 C
1(
b101 D
b1111 =
1,
#2470
0,
#2483
b1 C
b10000 =
1,
#2496
0,
#2509
b10 C
b10001 =
1,
#2522
0,
#2535
b0 C
0(
b110 D
b10010 =
1,
#2548
0,
#2561
b1 C
b10011 =
1,
#2574
0,
#2587
b10 C
b10100 =
1,
#2600
0,
#2613
b0 C
1(
b111 D
b10101 =
1,
#2626
0,
#2639
b1 C
b10110 =
1,
#2652
0,
#2665
b10 C
b10111 =
1,
#2678
0,
#2691
b0 C
0(
b1000 D
b11000 =
1,
#2704
0,
#2717
b1 C
b11001 =
1,
#2730
0,
#2743
b10 C
b11010 =
1,
#2756
0,
#2769
b0 C
1(
b1001 D
b11011 =
1,
#2782
0,
#2795
b1 C
b11100 =
1,
#2808
0,
#2821
b10 C
b11101 =
1,
#2834
0,
#2847
b0 C
0(
b1010 D
b11110 =
1,
#2860
0,
#2873
b11111 =
1,
#2886
0,
#2899
b100000 =
1,
#2912
0,
#2925
b100001 =
1,
#2938
0,
#2951
b100010 =
1,
#2964
0,
#2977
b100011 =
1,
#2990
0,
#3003
b0 D
b0 <
b100100 =
b0 ?
04
0$
1,
#3010
0)
b1 -
#3016
0,
#3029
b0 !
b0 A
b0 =
1,
